docs/changelog.rst
docs/conf.py
docs/contributing.rst
docs/example-api.rst
docs/example-wide-pages.rst
docs/index.rst
docs/installation.rst
docs/usage.rst
sphinx_audeering_theme/__init__.py
sphinx_audeering_theme/breadcrumbs.html
sphinx_audeering_theme/footer.html
sphinx_audeering_theme/layout.html
sphinx_audeering_theme/search.html
sphinx_audeering_theme/searchbox.html
sphinx_audeering_theme/theme.conf
sphinx_audeering_theme/versions.html
sphinx_audeering_theme/static/favicon.png
sphinx_audeering_theme/static/css/audeering-wide.css
sphinx_audeering_theme/static/css/audeering.css
sphinx_audeering_theme/static/css/badge_only.css
sphinx_audeering_theme/static/css/theme.css
sphinx_audeering_theme/static/fonts/FontAwesome.otf
sphinx_audeering_theme/static/fonts/Inconsolata-Bold.ttf
sphinx_audeering_theme/static/fonts/Inconsolata-Regular.ttf
sphinx_audeering_theme/static/fonts/Inconsolata.ttf
sphinx_audeering_theme/static/fonts/Lato-Bold.ttf
sphinx_audeering_theme/static/fonts/Lato-Regular.ttf
sphinx_audeering_theme/static/fonts/RobotoSlab-Bold.ttf
sphinx_audeering_theme/static/fonts/RobotoSlab-Regular.ttf
sphinx_audeering_theme/static/fonts/fontawesome-webfont.eot
sphinx_audeering_theme/static/fonts/fontawesome-webfont.svg
sphinx_audeering_theme/static/fonts/fontawesome-webfont.ttf
sphinx_audeering_theme/static/fonts/fontawesome-webfont.woff
sphinx_audeering_theme/static/fonts/fontawesome-webfont.woff2
sphinx_audeering_theme/static/fonts/Lato/lato-bold.eot
sphinx_audeering_theme/static/fonts/Lato/lato-bold.ttf
sphinx_audeering_theme/static/fonts/Lato/lato-bold.woff
sphinx_audeering_theme/static/fonts/Lato/lato-bold.woff2
sphinx_audeering_theme/static/fonts/Lato/lato-bolditalic.eot
sphinx_audeering_theme/static/fonts/Lato/lato-bolditalic.ttf
sphinx_audeering_theme/static/fonts/Lato/lato-bolditalic.woff
sphinx_audeering_theme/static/fonts/Lato/lato-bolditalic.woff2
sphinx_audeering_theme/static/fonts/Lato/lato-italic.eot
sphinx_audeering_theme-1.4.1.dist-info/licenses/LICENSE
sphinx_audeering_theme-1.4.1.dist-info/METADATA
sphinx_audeering_theme-1.4.1.dist-info/WHEEL
sphinx_audeering_theme-1.4.1.dist-info/entry_points.txt
sphinx_audeering_theme-1.4.1.dist-info/top_level.txt
sphinx_audeering_theme-1.4.1.dist-info/RECORD
