Metadata-Version: 2.4
Name: sphinx_audeering_theme
Version: 1.4.1
Summary: Sphinx documentation audEERING theme
Author-email: Hagen Wierstorf <hwierstorf@audeering.com>
License: MIT License
Project-URL: repository, https://github.com/audeering/sphinx-audeering-theme/
Project-URL: documentation, https://audeering.github.io/sphinx-audeering-theme/
Keywords: sphinx,documentation,html
Classifier: Development Status :: 5 - Production/Stable
Classifier: Intended Audience :: Science/Research
Classifier: Intended Audience :: Developers
Classifier: License :: OSI Approved :: MIT License
Classifier: Operating System :: OS Independent
Classifier: Programming Language :: Python
Classifier: Programming Language :: Python :: 3
Classifier: Programming Language :: Python :: 3.10
Classifier: Programming Language :: Python :: 3.11
Classifier: Programming Language :: Python :: 3.12
Classifier: Programming Language :: Python :: 3.13
Classifier: Topic :: Scientific/Engineering
Requires-Python: >=3.10
License-File: LICENSE
Requires-Dist: sphinx>=6.0.0
Dynamic: license-file
